django_states/__init__.py
django_states/apps.py
django_states/conf.py
django_states/exceptions.py
django_states/fields.py
django_states/log.py
django_states/machine.py
django_states/management/__init__.py
django_states/management/commands/__init__.py
django_states/management/commands/graph_states2.py
django_states/model_methods.py
django_states/models.py
django_states/signals.py
django_states/templatetags/__init__.py
django_states/templatetags/django_states.py
django_states/urls.py
django_states/views.py
django_states3-3.0.1.dist-info/LICENSE.txt
django_states3-3.0.1.dist-info/WHEEL
django_states3-3.0.1.dist-info/METADATA
django_states3-3.0.1.dist-info/RECORD
